[
   {
      "name" : "alt-image",
      "link" : "view/assets/image/b_a.jpg",
      "event" : ["all","lunes"]
   },
   {
      "name" : "alt-image",
      "link" : "view/assets/image/b_b.jpg",
      "event" : ["all"]
   },
   {
      "name" : "alt-image",
      "link" : "view/assets/image/b_c.jpg",
      "event" : ["all","lunes"]
   },
   {
      "name" : "alt-image",
      "link" : "view/assets/image/b_d.jpg",
      "event" : ["all","lunes"]
   },
   {
      "name" : "alt-image",
      "link" : "view/assets/image/b_e.jpg",
      "event" : ["all","martes"]
   },
   {
      "name" : "alt-image",
      "link" : "view/assets/image/b_f.jpg",
      "event" : ["all","lunes"]
   },
   {
      "name" : "alt-image",
      "link" : "view/assets/image/b_g.jpg",
      "event" : ["all","martes"]
   },
   {
      "name" : "alt-image",
      "link" : "view/assets/image/b_h.jpg",
      "event" : ["all","lunes"]
   },
   {
      "name" : "alt-image",
      "link" : "view/assets/image/b_i.jpg",
      "event" : ["all","lunes"]
   },
   {
      "name" : "alt-image",
      "link" : "view/assets/image/b_n.jpg",
      "event" : ["all","martes"]
   },
   {
      "name" : "alt-image",
      "link" : "view/assets/image/b_m.jpg",
      "event" : ["all","lunes"]
   },
   {
      "name" : "alt-image",
      "link" : "view/assets/image/b_l.jpg",
      "event" : ["all","lunes"]
   }
]
